rpm_uploader/__init__.py
rpm_uploader-0.2.1.dist-info/DESCRIPTION.rst
rpm_uploader-0.2.1.dist-info/entry_points.txt
rpm_uploader-0.2.1.dist-info/METADATA
rpm_uploader-0.2.1.dist-info/metadata.json
rpm_uploader-0.2.1.dist-info/RECORD
rpm_uploader-0.2.1.dist-info/top_level.txt
rpm_uploader-0.2.1.dist-info/WHEEL
