Metadata-Version: 2.0
Name: rpm-uploader
Version: 0.2.1
Summary: A tool to upload rpms into repositories.
Home-page: https://github.com/Guavus/rpm-uploader
Author: Damien Dube
Author-email: pypa-dev@googlegroups.com
License: MIT
Keywords: rpm
Platform: UNKNOWN
Classifier: Development Status :: 3 - Alpha
Classifier: Intended Audience :: Developers
Classifier: Topic :: Software Development :: Build Tools
Classifier: License :: OSI Approved :: MIT License
Classifier: Programming Language :: Python :: 2
Classifier: Programming Language :: Python :: 2.6
Classifier: Programming Language :: Python :: 2.7
Classifier: Programming Language :: Python :: 3
Classifier: Programming Language :: Python :: 3.2
Classifier: Programming Language :: Python :: 3.3
Classifier: Programming Language :: Python :: 3.4
Requires-Dist: setuptools
Requires-Dist: bottle
